setup.py
cashed/__init__.py
cashed/cache.py
cashed.egg-info/PKG-INFO
cashed.egg-info/SOURCES.txt
cashed.egg-info/dependency_links.txt
cashed.egg-info/top_level.txt
tests/__init__.py
tests/test_simple.py