Metadata-Version: 1.0
Name: cashed
Version: 0.2.0
Summary: Simple caching using decorators
Home-page: https://github.com/jaemk/cashed
Author: James Kominick
Author-email: james.kominick@gmail.com
License: MIT
Platform: UNKNOWN
